errorbuddy/__init__.py
errorbuddy/cli.py
errorbuddy/explainer.py
errorbuddy/rules.py
errorbuddy-0.1.1.dist-info/METADATA
errorbuddy-0.1.1.dist-info/WHEEL
errorbuddy-0.1.1.dist-info/entry_points.txt
errorbuddy-0.1.1.dist-info/top_level.txt
errorbuddy-0.1.1.dist-info/RECORD
