Metadata-Version: 2.4
Name: errorbuddy
Version: 0.1.1
Summary: Explain Python errors in simple English
Author: Hardik Dhingra
License: MIT
Requires-Python: >=3.8
